typer_di/__init__.py
typer_di/_create_di_wrapper.py
typer_di/_depends.py
typer_di/_method_builder.py
typer_di/_typer_di.py
typer_di/compat.py
typer_di/py.typed
typer_di-0.1.3.dist-info/LICENSE.txt
typer_di-0.1.3.dist-info/METADATA
typer_di-0.1.3.dist-info/WHEEL
typer_di-0.1.3.dist-info/RECORD
