Metadata-Version: 2.3
Name: typer-di
Version: 0.1.3
Summary: Extension for `typer` for dependency injection like in FastAPI
License: LICENCE.txt
Author: Evgeniy A. Cymbalyuk
Author-email: cimbaluk@gmail.com
Requires-Python: >=3.7
Classifier: License :: Other/Proprietary License
Classifier: Programming Language :: Python :: 3
Classifier: Programming Language :: Python :: 3.7
Classifier: Programming Language :: Python :: 3.8
Classifier: Programming Language :: Python :: 3.9
Classifier: Programming Language :: Python :: 3.10
Classifier: Programming Language :: Python :: 3.11
Classifier: Programming Language :: Python :: 3.12
Classifier: Programming Language :: Python :: 3.13
Requires-Dist: typer-slim (>=0.9.0)
Requires-Dist: typing-extensions (>=4.7.1) ; python_version < "3.10"
